transmogripy/__init__.py
transmogripy/__util.py
transmogripy/convert.py
transmogripy/filter_multiline_comments.py
transmogripy/rule.py
transmogripy/rules.py
transmogripy/segment.py
transmogripy/trans_dir.py
transmogripy-1.2.0.dist-info/LICENSE
transmogripy-1.2.0.dist-info/METADATA
transmogripy-1.2.0.dist-info/WHEEL
transmogripy-1.2.0.dist-info/top_level.txt
transmogripy-1.2.0.dist-info/RECORD
