Metadata-Version: 2.1
Name: transmogripy
Version: 1.2.0
Summary: tool to convert short pascal scripts to python
Home-page: https://github.com/talos-gis/transmogripy
Author: Ben Avrahami
Author-email: avrahami.ben@gmail.com
License: MIT
Platform: UNKNOWN
Classifier: Development Status :: 5 - Production/Stable
Classifier: Intended Audience :: Developers
Classifier: Intended Audience :: Science/Research
Classifier: License :: OSI Approved :: MIT License
Classifier: Operating System :: OS Independent
Classifier: Programming Language :: Python :: 3
Requires-Python: >=3.6.0
